vscode_multi/__init__.py
vscode_multi/__main__.py
vscode_multi/_version.py
vscode_multi/cli.py
vscode_multi/cli_helpers.py
vscode_multi/errors.py
vscode_multi/git_helpers.py
vscode_multi/git_merge_branch.py
vscode_multi/git_run.py
vscode_multi/git_set_branch.py
vscode_multi/ignore_files.py
vscode_multi/init.py
vscode_multi/init_readme.py
vscode_multi/logging.py
vscode_multi/paths.py
vscode_multi/repos.py
vscode_multi/rules.py
vscode_multi/settings.py
vscode_multi/sync.py
vscode_multi/sync_claude.py
vscode_multi/sync_ruff.py
vscode_multi/sync_vscode.py
vscode_multi/sync_vscode_extensions.py
vscode_multi/sync_vscode_helpers.py
vscode_multi/sync_vscode_launch.py
vscode_multi/sync_vscode_settings.py
vscode_multi/sync_vscode_tasks.py
vscode_multi/utils.py
vscode_multi-2.1.4.dist-info/METADATA
vscode_multi-2.1.4.dist-info/WHEEL
vscode_multi-2.1.4.dist-info/entry_points.txt
vscode_multi-2.1.4.dist-info/licenses/LICENSE
vscode_multi-2.1.4.dist-info/RECORD
